setup.py
tags/__init__.py
tags/tags.py
tags/widgets.py
tags.egg-info/PKG-INFO
tags.egg-info/SOURCES.txt
tags.egg-info/dependency_links.txt
tags.egg-info/top_level.txt