Metadata-Version: 1.0
Name: tags
Version: 0.0.3
Summary: A toolkit to create HTML code with python
Home-page: http://pypi.python.org/pypi/tags
Author: Patrick Sabin
Author-email: patricksabin@gmx.at
License: UNKNOWN
Platform: UNKNOWN
Classifier: Environment :: Web Environment
Classifier: Intended Audience :: Developers
Classifier: Topic :: Software Development :: Libraries :: Python Modules
Classifier: Topic :: Text Processing :: Markup :: HTML
Classifier: Programming Language :: Python
Classifier: Operating System :: OS Independent
Classifier: License :: OSI Approved :: GNU General Public License (GPL)
Classifier: Development Status :: 2 - Pre-Alpha
